{
  "id": "133710",
  "url": "http://127.0.0.1:5500/detail.html?src=api&id=133710",
  "tieuDe": "Quy định giá sản phẩm, dịch vụ công ích thủy lợi giai đoạn 2018-2020 trên địa bàn tỉnh Gia Lai.",
  "soHieu": "04/2019/QĐ-UBND",
  "ngayBanHanh": "14/01/2019",
  "ngayHieuLuc": "24/01/2019",
  "loaiVanBan": "Quyết định",
  "coQuanBanHanh": "Ủy ban nhân dân tỉnh Gia Lai",
  "tinhTrang": "Hết hiệu lực toàn bộ",
  "nganh": "Nông nghiệp và phát triển nông thôn",
  "linhVuc": "Thủy lợi",
  "noiDung": "<table class=\"detailcontent\" width=\"100%\" border=\"0\" id=\"content\">\r\n                <tr>\r\n                    <td colspan=\"3\">\r\n                        <div align=\"justify\">\r\n                            <p style=\"text-align:center;\">\n\t<strong>QUYẾT ĐỊNH</strong></p>\n<p style=\"text-align:center;\">\n\t<strong>            Quy định giá sản phẩm, dịch vụ công ích thủy lợi giai đoạn </strong></p>\n<p style=\"text-align:center;\">\n\t<strong>                                2018-2020 trên địa bàn tỉnh Gia Lai.</strong></p>\n<p align=\"center\">\n\t<strong>_____________________________</strong></p>\n<p align=\"center\">\n\t<strong>ỦY BAN NHÂN DÂN TỈNH </strong><strong>GIA LAI</strong></p>\n<p>\n\t<em>          Căn cứ Luật Tổ chức Chính quyền địa phương năm 2015;</em></p>\n<p>\n\t<em>          Căn cứ Luật Giá năm 2012;</em></p>\n<p>\n\t<em>          Căn cứ Luật Ngân sách nhà nước năm 2015;</em></p>\n<p>\n\t          <em>Căn cứ</em><em> Luật Thủy lợi năm </em><em>2017</em><em>;</em></p>\n<p>\n\t          <em>Căn cứ Nghị định số</em><em> 96</em><em>/2018/NĐ-CP </em> <em>ngày 30/</em><em>6/</em><em>2018</em><em> của Chính Phủ về việc quy định chi tiết về sản phẩm, dịch vụ thủy lợi và hỗ trợ tiền sử dụng sản phẩm, dịch vụ công ích thủy lợi;</em></p>\n<p>\n\t          <em>Thực hiện Quyết định số 1050a/QĐ-BTC </em><em>ngày 30/6/</em><em>2018</em><em> của Bộ Trưởng Bộ Tài chính về giá tối đa sản phẩm, dịch vụ công ích thủy lợi giai đoạn 2018-2020;</em></p>\n<p>\n\t<em>          Căn cứ Nghị Quyết số 95/2018/NQ-HĐND ngày 06/12/2018 của Hội đồng nhân dân tỉnh Gia Lai thông qua giá sản phẩm, dịch vụ công ích thủy lợi giai đoạn 2018-2020 trên địa bàn tỉnh Gia Lai;</em></p>\n<p>\n\t<em>          Theo đề nghị của Giám đốc Sở Nông nghiệp và Phát triển nông thôn tại Tờ trình số 01/TTr-SNNPTNT ngày 03/01/2019.</em></p>\n<p align=\"center\">\n\t<strong>QUYẾT ĐỊNH:</strong></p>\n<p>\n\t          <strong>Điều 1. Phạm vi điều chỉnh, đối tượng áp dụng</strong></p>\n<p>\n\t          1. Phạm vi điều chỉnh:</p>\n<p>\n\t          Quyết định này quy định giá sản phẩm, dịch vụ công ích thủy lợi giai đoạn 2018-2020 trên địa bàn tỉnh Gia Lai.</p>\n<p>\n\t          2. Đối tượng áp dụng:</p>\n<p>\n\t          a) Cơ quan nhà nước.</p>\n<p>\n\t          b) Chủ sở hữu và cơ quan quản lý công trình thủy lợi.</p>\n<p>\n\t          c) Tổ chức, cá nhân khai thác công trình thủy lợi; tổ chức, cá nhân sử dụng sản phẩm, dịch vụ công ích thủy lợi.</p>\n<p>\n\t          d) Các tổ chức cá nhân khác có liên quan.</p>\n<p>\n\t          <strong>Điều 2. Giá sản phẩm, dịch vụ công ích thủy lợi</strong></p>\n<p>\n\t          1. Biểu giá sản phẩm, dịch vụ công ích thủy lợi đối với đất trồng lúa:</p>\n<table border=\"1\" cellpadding=\"0\" cellspacing=\"0\" style=\"width:605px;\" width=\"605\">\n\t<tbody>\n\t\t<tr>\n\t\t\t<td style=\"width:57px;height:71px;\">\n\t\t\t\t<p align=\"center\">\n\t\t\t\t\t<strong>S</strong><strong>TT</strong></p>\n\t\t\t</td>\n\t\t\t<td style=\"width:406px;height:71px;\">\n\t\t\t\t<p align=\"center\">\n\t\t\t\t\t<strong>B</strong><strong>iện pháp công trình</strong></p>\n\t\t\t</td>\n\t\t\t<td style=\"width:142px;height:71px;\">\n\t\t\t\t<p align=\"center\">\n\t\t\t\t\t<strong>Mức giá</strong><br>\n\t\t\t\t\t<strong>(1.000 đồng/ha/vụ)</strong></p>\n\t\t\t</td>\n\t\t</tr>\n\t\t<tr>\n\t\t\t<td style=\"width:57px;height:28px;\">\n\t\t\t\t<p align=\"center\">\n\t\t\t\t\t 1</p>\n\t\t\t</td>\n\t\t\t<td style=\"width:406px;height:28px;\">\n\t\t\t\t<p>\n\t\t\t\t\tTưới tiêu bằng động lực</p>\n\t\t\t</td>\n\t\t\t<td style=\"width:142px;height:28px;\">\n\t\t\t\t<p align=\"center\">\n\t\t\t\t\t1.629</p>\n\t\t\t</td>\n\t\t</tr>\n\t\t<tr>\n\t\t\t<td style=\"width:57px;height:27px;\">\n\t\t\t\t<p align=\"center\">\n\t\t\t\t\t 2</p>\n\t\t\t</td>\n\t\t\t<td style=\"width:406px;height:27px;\">\n\t\t\t\t<p>\n\t\t\t\t\tTưới tiêu bằng trọng lực</p>\n\t\t\t</td>\n\t\t\t<td style=\"width:142px;height:27px;\">\n\t\t\t\t<p align=\"center\">\n\t\t\t\t\t1.140</p>\n\t\t\t</td>\n\t\t</tr>\n\t\t<tr>\n\t\t\t<td style=\"width:57px;height:29px;\">\n\t\t\t\t<p align=\"center\">\n\t\t\t\t\t 3</p>\n\t\t\t</td>\n\t\t\t<td style=\"width:406px;height:29px;\">\n\t\t\t\t<p>\n\t\t\t\t\tTưới tiêu bằng trọng lực và kết hợp động lực hỗ trợ</p>\n\t\t\t</td>\n\t\t\t<td style=\"width:142px;height:29px;\">\n\t\t\t\t<p align=\"center\">\n\t\t\t\t\t1.385</p>\n\t\t\t</td>\n\t\t</tr>\n\t</tbody>\n</table>\n<p>\n\t          - Trường hợp tưới, tiêu chủ động một phần thì thu bằng 60% mức giá tại Biểu trên.</p>\n<p>\n\t          - Trường hợp chỉ tạo nguồn tưới, tiêu bằng trọng lực thì thu bằng 40% mức giá tại Biểu trên.</p>\n<p>\n\t          - Trường hợp chỉ tạo nguồn tưới, tiêu bằng động lực thì thu bằng 50% mức giá tại Biểu trên.</p>\n<p>\n\t          - Trường hợp phải tạo nguồn từ bậc 2 trở lên đối với các công trình được xây dựng theo quy hoạch được cấp có thẩm quyền phê duyệt, mức giá được tính tăng thêm 20% so với mức giá tại Biểu trên.</p>\n<p>\n\t          - Trường hợp phải tách riêng mức giá cho tưới, tiêu trên cùng một diện tích thì mức giá cho tưới được tính bằng 70%, cho tiêu được tính bằng 30% mức giá quy định tại Biểu trên.</p>\n<p>\n\t          2. Mức giá đối với diện tích trồng mạ, rau, màu, cây công nghiệp ngắn ngày kể cả cây vụ đông thì được tính bằng 40% mức giá thủy lợi đối với đất trồng lúa.</p>\n<p>\n\t          3. Mức giá đối với cấp nước để chăn nuôi, nuôi trồng thủy sản và cấp nước tưới cho cây công nghiệp dài ngày, cây ăn quả, hoa và cây dược liệu được tính theo Biểu sau:</p>\n<table border=\"0\" cellpadding=\"0\" cellspacing=\"0\" width=\"595\">\n\t<tbody>\n\t\t<tr>\n\t\t\t<td rowspan=\"2\" style=\"width:57px;height:47px;\">\n\t\t\t\t<p>\n\t\t\t\t\t<strong>S</strong><strong>TT</strong></p>\n\t\t\t</td>\n\t\t\t<td rowspan=\"2\" style=\"width:198px;height:47px;\">\n\t\t\t\t<p align=\"center\">\n\t\t\t\t\t<strong>Các đối tượng dùng nước</strong></p>\n\t\t\t</td>\n\t\t\t<td rowspan=\"2\" style=\"width:113px;height:47px;\">\n\t\t\t\t<p align=\"center\">\n\t\t\t\t\t<strong>Đơn vị</strong></p>\n\t\t\t</td>\n\t\t\t<td colspan=\"3\" style=\"width:227px;height:47px;\">\n\t\t\t\t<p align=\"center\">\n\t\t\t\t\t<strong>Mức giá </strong><strong>theo các</strong><strong> bi</strong><strong>ện pháp công trình</strong></p>\n\t\t\t</td>\n\t\t</tr>\n\t\t<tr>\n\t\t\t<td style=\"width:95px;height:46px;\">\n\t\t\t\t<p align=\"center\">\n\t\t\t\t\t<strong>Bơm điện</strong></p>\n\t\t\t</td>\n\t\t\t<td colspan=\"2\" style=\"width:132px;height:46px;\">\n\t\t\t\t<p align=\"center\">\n\t\t\t\t\t<strong>Hồ đập, kênh cống</strong></p>\n\t\t\t</td>\n\t\t</tr>\n\t\t<tr>\n\t\t\t<td style=\"width:57px;height:29px;\">\n\t\t\t\t<p align=\"center\">\n\t\t\t\t\t1</p>\n\t\t\t</td>\n\t\t\t<td style=\"width:198px;height:29px;\">\n\t\t\t\t<p>\n\t\t\t\t\tCấp nước cho chăn nuôi</p>\n\t\t\t</td>\n\t\t\t<td style=\"width:113px;height:29px;\">\n\t\t\t\t<p>\n\t\t\t\t\tđồng/m<sup>3</sup></p>\n\t\t\t</td>\n\t\t\t<td style=\"width:95px;height:29px;\">\n\t\t\t\t<p align=\"center\">\n\t\t\t\t\t1.320</p>\n\t\t\t</td>\n\t\t\t<td colspan=\"2\" style=\"width:132px;height:29px;\">\n\t\t\t\t<p align=\"center\">\n\t\t\t\t\t900</p>\n\t\t\t</td>\n\t\t</tr>\n\t\t<tr>\n\t\t\t<td rowspan=\"2\" style=\"width:57px;height:28px;\">\n\t\t\t\t<p align=\"center\">\n\t\t\t\t\t2</p>\n\t\t\t</td>\n\t\t\t<td rowspan=\"2\" style=\"width:198px;height:28px;\">\n\t\t\t\t<p>\n\t\t\t\t\tCấp nước để nuôi trồng thủy sản</p>\n\t\t\t</td>\n\t\t\t<td style=\"width:113px;height:28px;\">\n\t\t\t\t<p>\n\t\t\t\t\tđồng/m<sup>3</sup></p>\n\t\t\t</td>\n\t\t\t<td style=\"width:95px;height:28px;\">\n\t\t\t\t<p align=\"center\">\n\t\t\t\t\t840</p>\n\t\t\t</td>\n\t\t\t<td colspan=\"2\" style=\"width:132px;height:28px;\">\n\t\t\t\t<p align=\"center\">\n\t\t\t\t\t600</p>\n\t\t\t</td>\n\t\t</tr>\n\t\t<tr>\n\t\t\t<td style=\"width:113px;height:46px;\">\n\t\t\t\t<p>\n\t\t\t\t\tđồng/m<sup>2</sup> mặt thoáng/năm</p>\n\t\t\t</td>\n\t\t\t<td colspan=\"3\" style=\"width:227px;height:46px;\">\n\t\t\t\t<p align=\"center\">\n\t\t\t\t\t250</p>\n\t\t\t</td>\n\t\t</tr>\n\t\t<tr>\n\t\t\t<td style=\"width:57px;height:98px;\">\n\t\t\t\t<p align=\"center\">\n\t\t\t\t\t3</p>\n\t\t\t</td>\n\t\t\t<td style=\"width:198px;height:98px;\">\n\t\t\t\t<p>\n\t\t\t\t\tCấp nước tưới các cây công nghiệp dài ngày, cây ăn quả, hoa và cây dược liệu</p>\n\t\t\t</td>\n\t\t\t<td style=\"width:113px;height:98px;\">\n\t\t\t\t<p>\n\t\t\t\t\tđồng/m<sup>3</sup></p>\n\t\t\t</td>\n\t\t\t<td colspan=\"2\" style=\"width:144px;height:98px;\">\n\t\t\t\t<p align=\"center\">\n\t\t\t\t\t </p>\n\t\t\t\t<p align=\"center\">\n\t\t\t\t\t1.020</p>\n\t\t\t</td>\n\t\t\t<td style=\"width:83px;height:98px;\">\n\t\t\t\t<p align=\"center\">\n\t\t\t\t\t </p>\n\t\t\t\t<p align=\"center\">\n\t\t\t\t\t840</p>\n\t\t\t</td>\n\t\t</tr>\n\t\t<tr height=\"0\">\n\t\t\t<td>\n\t\t\t\t </td>\n\t\t\t<td>\n\t\t\t\t </td>\n\t\t\t<td>\n\t\t\t\t </td>\n\t\t\t<td>\n\t\t\t\t </td>\n\t\t\t<td>\n\t\t\t\t </td>\n\t\t\t<td>\n\t\t\t\t </td>\n\t\t</tr>\n\t</tbody>\n</table>\n<p>\n\t             - Trường hợp cấp nước tưới cho cây công nghiệp dài ngày, cây ăn quả, hoa, cây dược liệu nếu không tính được theo mét khối (m<sup>3</sup>) thì tính theo diện tích (ha), mức giá bằng 80% mức giá sản phẩm, dịch vụ công ích thủy lợi đối với đất trồng lúa cho một năm theo quy định.</p>\n<p>\n\t          - Tiêu, thoát nước khu vực nông thôn và đô thị trừ vùng nội thị mức giá bằng 5% mức giá sản phẩm, dịch vụ công ích thủy lợi của tưới đối với đất trồng lúa/vụ.</p>\n<p>\n\t          4. Giá sản phẩm, dịch vụ công ích thủy lợi quy định tại Khoản 1, Khoản 2, Khoản 3 Điều này là giá không có thuế giá trị gia tăng và được tính từ điểm giao nhận sản phẩm, dịch vụ thủy lợi giữa tổ chức, cá nhân cung cấp và tổ chức, cá nhân sử dụng sản phẩm, dịch vụ đến vị trí công trình đầu mối ở vị trí khởi đầu.</p>\n<p>\n\t          5. Các khoản chi phí từ điểm giao nhận sản phẩm, dịch vụ thủy lợi đến khu đất canh tác thuộc trách nhiệm các tổ chức, cá nhân sử dụng sản phẩm, dịch vụ thủy lợi.</p>\n<p>\n\t          <strong>Điều 3. Hiệu lực thi hành </strong></p>\n<p>\n\t          Quyết định này có hiệu lực thi hành kể từ ngày 24 tháng 01 năm 2019 và thay thế Quyết định số 34/2017/QĐ-UBND ngày 26/12/2017 của Ủy ban nhân dân tỉnh Gia Lai quy định cụ thể đối với giá sản phẩm, dịch vụ công ích thủy lợi và giá dịch vụ lấy nước từ sau cống đầu kênh đến mặt ruộng do địa phương quản lý áp dụng trên địa bàn tỉnh Gia Lai.</p>\n<p>\n\t<strong>          Điều 4. Tổ chức thực hiện</strong></p>\n<p>\n\t<strong>          </strong>1. Giao Sở Nông nghiệp và Phát triển nông thôn phối hợp với Sở Tài chính và các sở, ngành có liên quan hướng dẫn thực hiện Quyết định này.</p>\n<p>\n\t<strong>          </strong>2. Các đơn vị cung ứng sản phẩm, dịch vụ công ích thủy lợi phải thực hiện niêm yết giá, công khai thông tin về giá theo quy định pháp luật về giá.</p>\n<p>\n\t<strong>          </strong>3. Chánh Văn phòng UBND tỉnh; Giám đốc các Sở: Tài chính, Nông nghiệp và Phát triển nông thôn; Cục trưởng Cục Thuế tỉnh; Chủ tịch Ủy ban nhân dân các huyện, thị xã, thành phố; các cơ quan, đơn vị và tổ chức, cá nhân có liên quan chịu trách nhiệm thi hành Quyết định này./.</p>\r\n                        </div>\r\n                    </td>\r\n                </tr>\r\n\r\n            </table>"
}