{
  "id": "139036",
  "url": "http://127.0.0.1:5500/detail.html?src=api&id=139036",
  "tieuDe": "Nghị quyết Điều chỉnh quy hoạch sử dụng đất đến năm 2020, kế hoạch sử dụng đất kỳ cuối (2016 - 2020) tỉnh Bình Phước",
  "soHieu": "14/2019/NQ-HĐND",
  "ngayBanHanh": "05/07/2019",
  "ngayHieuLuc": "15/07/2019",
  "loaiVanBan": "Nghị quyết",
  "coQuanBanHanh": "Hội đồng Nhân dân tỉnh Bình Phước",
  "tinhTrang": "Còn hiệu lực",
  "nganh": "Tài nguyên và Môi trường",
  "linhVuc": "Đất đai",
  "noiDung": "<table class=\"detailcontent\" width=\"100%\" border=\"0\" id=\"content\">\r\n                <tr>\r\n                    <td colspan=\"3\">\r\n                        <div align=\"justify\">\r\n                            <p align=\"center\">\n\t<strong>NGHỊ QUYẾT </strong></p>\n<p align=\"center\">\n\t<strong>Điều chỉnh quy hoạch sử dụng đất đến năm 2020, </strong></p>\n<p align=\"center\">\n\t<strong>kế hoạch sử dụng <u>đất kỳ cuối (2016 - 2020)</u> tỉnh Bình Phước</strong></p>\n<p>\n\t </p>\n<p>\n\t </p>\n<p align=\"center\">\n\t<strong>HỘI ĐỒNG NHÂN DÂN TỈNH BÌNH PHƯỚC</strong></p>\n<p align=\"center\">\n\t<strong>KHÓA IX, KỲ HỌP THỨ TÁM</strong></p>\n<p align=\"center\">\n\t </p>\n<p style=\"text-align:justify;\">\n\t<em>Căn cứ Luật Tổ chức chính quyền địa phương ngày 19 tháng 6 năm 2015;  </em></p>\n<p style=\"text-align:justify;\">\n\t<em>Căn cứ Luật Ban hành văn bản quy phạm pháp luật ngày 22 tháng 6 năm 2015;</em></p>\n<p style=\"text-align:justify;\">\n\t<em>Căn cứ Luật Đất đai ngày 29 tháng 11 năm 2013; </em></p>\n<p style=\"text-align:justify;\">\n\t<em>Căn cứ </em><em>Nghị quyết số 134/2016/QH13 ngày 09 tháng 4 năm 2016 của Quốc hội về điều chỉnh quy hoạch sử dụng đất đến năm 2020, lập kế hoạch sử dụng đất kỳ cuối (2016-2020) cấp Quốc gia</em><em>; </em></p>\n<p style=\"text-align:justify;\">\n\t<em>Căn cứ Nghị định số 43/2014/NĐ-CP ngày 15 tháng 5 năm 2014 của Chính phủ về quy định chi tiết thi hành một số điều của Luật Đất đai;</em></p>\n<p style=\"text-align:justify;\">\n\t<em>Căn cứ Nghị định số 01/2017/NĐ-CP ngày 06 tháng 01 năm 2017 của Chính phủ về sửa đổi, bổ sung một số Nghị định quy định chi tiết thi hành Luật Đất đai; </em></p>\n<p style=\"text-align:justify;\">\n\t<em>Căn cứ Thông tư số 29/2014/TT-BTNMT ngày 02 tháng 6 năm 2014 của Bộ trưởng Bộ Tài nguyên và Môi trường quy định chi tiết việc lập, điều chỉnh quy hoạch, kế hoạch sử dụng đất;</em></p>\n<p style=\"text-align:justify;\">\n\t<em>Xét Tờ trình số 21/TTr-UBND ngày 06 tháng 6 năm 2019 của Ủy ban nhân dân tỉnh; Báo cáo thẩm tra số 23/BC-HĐND-KTNS ngày 20 tháng 6 năm 2019 của Ban kinh tế - ngân sách Hội đồng nhân dân tỉnh; ý kiến thảo luận của đại biểu Hội đồng nhân dân tỉnh tại kỳ họp.</em></p>\n<p align=\"center\">\n\t </p>\n<p align=\"center\">\n\t<strong>QUYẾT NGHỊ:</strong></p>\n<p style=\"text-align:justify;\">\n\t<strong>Điều 1.</strong> Thông qua điều chỉnh Quy hoạch sử dụng đất đến năm 2020, Kế hoạch sử dụng đất kỳ cuối (2016 - 2020) tỉnh Bình Phước với các nội dung chủ yếu sau:</p>\n<p style=\"text-align:justify;\">\n\t1. Nội dung phương án điều chỉnh quy hoạch sử dụng đất đến năm 2020</p>\n<p style=\"text-align:justify;\">\n\ta) Diện tích, cơ cấu các loại đất</p>\n<p style=\"text-align:justify;\">\n\t- Diện tích đất nông nghiệp điều chỉnh quy hoạch là: 609.176 ha;</p>\n<p style=\"text-align:justify;\">\n\t- Diện tích đất phi nông nghiệp điều chỉnh quy hoạch là: 78.500 ha;</p>\n<p style=\"text-align:justify;\">\n\t- Diện tích đất chưa sử dụng điều chỉnh quy hoạch là: 0 ha.</p>\n<p align=\"center\">\n\t<em>(chi tiết tại phụ lục 01)</em></p>\n<p>\n\tb) Diện tích chuyển mục đích sử dụng đất</p>\n<p style=\"text-align:justify;\">\n\tDiện tích chuyển mục đích sử dụng đất trong cả kỳ điều chỉnh quy hoạch đất nông nghiệp chuyển sang đất phi nông nghiệp là: 20.735 ha; trong đó, kỳ đầu (2011 - 2015) là 4.379 ha; kỳ cuối (2016 - 2020) là 16.357 ha.</p>\n<p style=\"text-align:center;\">\n\t<em>(chi tiết tại phụ lục 02)</em></p>\n<p style=\"text-align:justify;\">\n\tc) Diện tích đất chưa sử dụng đưa vào sử dụng cho các mục đích</p>\n<p style=\"text-align:justify;\">\n\tDiện tích đất chưa sử dụng đưa vào sử dụng cho các mục đích trong kỳ điều chỉnh quy hoạch là: 834 ha; trong đó, kỳ đầu (2011 - 2015) là 830 ha; kỳ cuối (2016 - 2020) là 4 ha.</p>\n<p style=\"text-align:center;\">\n\t<em>(chi tiết tại phụ lục 03)</em></p>\n<p style=\"text-align:justify;\">\n\t2. Kế hoạch chuyển mục đích sử dụng đất kỳ cuối (2016-2020)</p>\n<p style=\"text-align:justify;\">\n\ta) Phân bổ diện tích các loại đất trong kỳ kế hoạch</p>\n<p style=\"text-align:justify;\">\n\t- Đất nông nghiệp:</p>\n<table border=\"1\" cellpadding=\"0\" cellspacing=\"0\" style=\"width:630px;\" width=\"630\">\n\t<tbody>\n\t\t<tr>\n\t\t\t<td style=\"width:121px;height:23px;\">\n\t\t\t\t<p align=\"center\">\n\t\t\t\t\tNăm</p>\n\t\t\t</td>\n\t\t\t<td style=\"width:107px;height:23px;\">\n\t\t\t\t<p align=\"center\">\n\t\t\t\t\t2016</p>\n\t\t\t</td>\n\t\t\t<td style=\"width:107px;height:23px;\">\n\t\t\t\t<p align=\"center\">\n\t\t\t\t\t2017</p>\n\t\t\t</td>\n\t\t\t<td style=\"width:107px;height:23px;\">\n\t\t\t\t<p align=\"center\">\n\t\t\t\t\t2018</p>\n\t\t\t</td>\n\t\t\t<td style=\"width:96px;height:23px;\">\n\t\t\t\t<p align=\"center\">\n\t\t\t\t\t2019</p>\n\t\t\t</td>\n\t\t\t<td style=\"width:93px;height:23px;\">\n\t\t\t\t<p align=\"center\">\n\t\t\t\t\t2020</p>\n\t\t\t</td>\n\t\t</tr>\n\t\t<tr>\n\t\t\t<td style=\"width:121px;height:23px;\">\n\t\t\t\t<p align=\"center\">\n\t\t\t\t\tDiện tích (ha)</p>\n\t\t\t</td>\n\t\t\t<td style=\"width:107px;height:23px;\">\n\t\t\t\t<p align=\"center\">\n\t\t\t\t\t616.783</p>\n\t\t\t</td>\n\t\t\t<td style=\"width:107px;height:23px;\">\n\t\t\t\t<p align=\"center\">\n\t\t\t\t\t613.669</p>\n\t\t\t</td>\n\t\t\t<td style=\"width:107px;height:23px;\">\n\t\t\t\t<p align=\"center\">\n\t\t\t\t\t612.711</p>\n\t\t\t</td>\n\t\t\t<td style=\"width:96px;height:23px;\">\n\t\t\t\t<p align=\"center\">\n\t\t\t\t\t611.168</p>\n\t\t\t</td>\n\t\t\t<td style=\"width:93px;height:23px;\">\n\t\t\t\t<p align=\"center\">\n\t\t\t\t\t609.176</p>\n\t\t\t</td>\n\t\t</tr>\n\t</tbody>\n</table>\n<p>\n\t- Đất phi nông nghiệp:</p>\n<table border=\"1\" cellpadding=\"0\" cellspacing=\"0\" style=\"width:631px;\" width=\"631\">\n\t<tbody>\n\t\t<tr>\n\t\t\t<td style=\"width:121px;\">\n\t\t\t\t<p align=\"center\">\n\t\t\t\t\tNăm</p>\n\t\t\t</td>\n\t\t\t<td style=\"width:107px;\">\n\t\t\t\t<p align=\"center\">\n\t\t\t\t\t2016</p>\n\t\t\t</td>\n\t\t\t<td style=\"width:107px;\">\n\t\t\t\t<p align=\"center\">\n\t\t\t\t\t2017</p>\n\t\t\t</td>\n\t\t\t<td style=\"width:107px;\">\n\t\t\t\t<p align=\"center\">\n\t\t\t\t\t2018</p>\n\t\t\t</td>\n\t\t\t<td style=\"width:96px;\">\n\t\t\t\t<p align=\"center\">\n\t\t\t\t\t2019</p>\n\t\t\t</td>\n\t\t\t<td style=\"width:95px;\">\n\t\t\t\t<p align=\"center\">\n\t\t\t\t\t2020</p>\n\t\t\t</td>\n\t\t</tr>\n\t\t<tr>\n\t\t\t<td style=\"width:121px;\">\n\t\t\t\t<p align=\"center\">\n\t\t\t\t\tDiện tích (ha)</p>\n\t\t\t</td>\n\t\t\t<td style=\"width:107px;\">\n\t\t\t\t<p align=\"center\">\n\t\t\t\t\t70.891</p>\n\t\t\t</td>\n\t\t\t<td style=\"width:107px;\">\n\t\t\t\t<p align=\"center\">\n\t\t\t\t\t74.005</p>\n\t\t\t</td>\n\t\t\t<td style=\"width:107px;\">\n\t\t\t\t<p align=\"center\">\n\t\t\t\t\t74.963</p>\n\t\t\t</td>\n\t\t\t<td style=\"width:96px;\">\n\t\t\t\t<p align=\"center\">\n\t\t\t\t\t76.508</p>\n\t\t\t</td>\n\t\t\t<td style=\"width:95px;\">\n\t\t\t\t<p align=\"center\">\n\t\t\t\t\t78.500</p>\n\t\t\t</td>\n\t\t</tr>\n\t</tbody>\n</table>\n<p>\n\t- Đất chưa sử dụng:</p>\n<table border=\"1\" cellpadding=\"0\" cellspacing=\"0\" style=\"width:631px;\" width=\"631\">\n\t<tbody>\n\t\t<tr>\n\t\t\t<td style=\"width:121px;\">\n\t\t\t\t<p align=\"center\">\n\t\t\t\t\tNăm</p>\n\t\t\t</td>\n\t\t\t<td style=\"width:106px;\">\n\t\t\t\t<p align=\"center\">\n\t\t\t\t\t2016</p>\n\t\t\t</td>\n\t\t\t<td style=\"width:106px;\">\n\t\t\t\t<p align=\"center\">\n\t\t\t\t\t2017</p>\n\t\t\t</td>\n\t\t\t<td style=\"width:106px;\">\n\t\t\t\t<p align=\"center\">\n\t\t\t\t\t2018</p>\n\t\t\t</td>\n\t\t\t<td style=\"width:97px;\">\n\t\t\t\t<p align=\"center\">\n\t\t\t\t\t2019</p>\n\t\t\t</td>\n\t\t\t<td style=\"width:95px;\">\n\t\t\t\t<p align=\"center\">\n\t\t\t\t\t2020</p>\n\t\t\t</td>\n\t\t</tr>\n\t\t<tr>\n\t\t\t<td style=\"width:121px;\">\n\t\t\t\t<p align=\"center\">\n\t\t\t\t\tDiện tích (ha)</p>\n\t\t\t</td>\n\t\t\t<td style=\"width:106px;\">\n\t\t\t\t<p align=\"center\">\n\t\t\t\t\t2</p>\n\t\t\t</td>\n\t\t\t<td style=\"width:106px;\">\n\t\t\t\t<p align=\"center\">\n\t\t\t\t\t2</p>\n\t\t\t</td>\n\t\t\t<td style=\"width:106px;\">\n\t\t\t\t<p align=\"center\">\n\t\t\t\t\t2</p>\n\t\t\t</td>\n\t\t\t<td style=\"width:97px;\">\n\t\t\t\t<p align=\"center\">\n\t\t\t\t\t0</p>\n\t\t\t</td>\n\t\t\t<td style=\"width:95px;\">\n\t\t\t\t<p align=\"center\">\n\t\t\t\t\t0</p>\n\t\t\t</td>\n\t\t</tr>\n\t</tbody>\n</table>\n<p align=\"center\">\n\t<em>(chi tiết tại phụ lục 04)</em></p>\n<p style=\"text-align:justify;\">\n\t          b) Kế hoạch chuyển mục đích sử dụng đất kỳ cuối</p>\n<p style=\"text-align:justify;\">\n\t          Diện tích chuyển mục đích sử dụng đất kỳ cuối từ đất nông nghiệp chuyển sang đất phi nông nghiệp như sau:</p>\n<table border=\"1\" cellpadding=\"0\" cellspacing=\"0\" style=\"width:631px;\" width=\"631\">\n\t<tbody>\n\t\t<tr>\n\t\t\t<td style=\"width:121px;\">\n\t\t\t\t<p align=\"center\">\n\t\t\t\t\tNăm</p>\n\t\t\t</td>\n\t\t\t<td style=\"width:106px;\">\n\t\t\t\t<p align=\"center\">\n\t\t\t\t\t2016</p>\n\t\t\t</td>\n\t\t\t<td style=\"width:106px;\">\n\t\t\t\t<p align=\"center\">\n\t\t\t\t\t2017</p>\n\t\t\t</td>\n\t\t\t<td style=\"width:106px;\">\n\t\t\t\t<p align=\"center\">\n\t\t\t\t\t2018</p>\n\t\t\t</td>\n\t\t\t<td style=\"width:97px;\">\n\t\t\t\t<p align=\"center\">\n\t\t\t\t\t2019</p>\n\t\t\t</td>\n\t\t\t<td style=\"width:95px;\">\n\t\t\t\t<p align=\"center\">\n\t\t\t\t\t2020</p>\n\t\t\t</td>\n\t\t</tr>\n\t\t<tr>\n\t\t\t<td style=\"width:121px;\">\n\t\t\t\t<p align=\"center\">\n\t\t\t\t\tDiện tích (ha)</p>\n\t\t\t</td>\n\t\t\t<td style=\"width:106px;\">\n\t\t\t\t<p align=\"center\">\n\t\t\t\t\t4.112</p>\n\t\t\t</td>\n\t\t\t<td style=\"width:106px;\">\n\t\t\t\t<p align=\"center\">\n\t\t\t\t\t2.677</p>\n\t\t\t</td>\n\t\t\t<td style=\"width:106px;\">\n\t\t\t\t<p align=\"center\">\n\t\t\t\t\t1.970</p>\n\t\t\t</td>\n\t\t\t<td style=\"width:97px;\">\n\t\t\t\t<p align=\"center\">\n\t\t\t\t\t2.929</p>\n\t\t\t</td>\n\t\t\t<td style=\"width:95px;\">\n\t\t\t\t<p align=\"center\">\n\t\t\t\t\t4.668</p>\n\t\t\t</td>\n\t\t</tr>\n\t</tbody>\n</table>\n<p align=\"center\">\n\t<em>(chi tiết tại phụ lục 05)</em></p>\n<p>\n\t          c) Kế hoạch đưa đất chưa sử dụng vào sử dụng</p>\n<table border=\"1\" cellpadding=\"0\" cellspacing=\"0\" style=\"width:631px;\" width=\"631\">\n\t<tbody>\n\t\t<tr>\n\t\t\t<td style=\"width:121px;\">\n\t\t\t\t<p align=\"center\">\n\t\t\t\t\tNăm</p>\n\t\t\t</td>\n\t\t\t<td style=\"width:106px;\">\n\t\t\t\t<p align=\"center\">\n\t\t\t\t\t2016</p>\n\t\t\t</td>\n\t\t\t<td style=\"width:106px;\">\n\t\t\t\t<p align=\"center\">\n\t\t\t\t\t2017</p>\n\t\t\t</td>\n\t\t\t<td style=\"width:106px;\">\n\t\t\t\t<p align=\"center\">\n\t\t\t\t\t2018</p>\n\t\t\t</td>\n\t\t\t<td style=\"width:97px;\">\n\t\t\t\t<p align=\"center\">\n\t\t\t\t\t2019</p>\n\t\t\t</td>\n\t\t\t<td style=\"width:95px;\">\n\t\t\t\t<p align=\"center\">\n\t\t\t\t\t2020</p>\n\t\t\t</td>\n\t\t</tr>\n\t\t<tr>\n\t\t\t<td style=\"width:121px;\">\n\t\t\t\t<p align=\"center\">\n\t\t\t\t\tDiện tích (ha)</p>\n\t\t\t</td>\n\t\t\t<td style=\"width:106px;\">\n\t\t\t\t<p align=\"center\">\n\t\t\t\t\t2</p>\n\t\t\t</td>\n\t\t\t<td style=\"width:106px;\">\n\t\t\t\t<p align=\"center\">\n\t\t\t\t\t0</p>\n\t\t\t</td>\n\t\t\t<td style=\"width:106px;\">\n\t\t\t\t<p align=\"center\">\n\t\t\t\t\t0</p>\n\t\t\t</td>\n\t\t\t<td style=\"width:97px;\">\n\t\t\t\t<p align=\"center\">\n\t\t\t\t\t2</p>\n\t\t\t</td>\n\t\t\t<td style=\"width:95px;\">\n\t\t\t\t<p align=\"center\">\n\t\t\t\t\t0</p>\n\t\t\t</td>\n\t\t</tr>\n\t</tbody>\n</table>\n<p style=\"text-align:center;\">\n\t<em>(chi tiết tại phụ lục 06)</em></p>\n<p style=\"text-align:justify;\">\n\t3. Chỉ tiêu quy hoạch đất lâm nghiệp đến năm 2020 trên địa bàn tỉnh thực hiện theo Nghị quyết số 149/NQ-CP ngày 13 tháng 12 năm 2018 của Chính phủ về Điều chỉnh Quy hoạch sử dụng đất đến năm 2020, kế hoạch sử dụng đất kỳ cuối (2016-2020) tỉnh Bình Phước.</p>\n<p style=\"text-align:justify;\">\n\t          <strong>Điều </strong><strong>2</strong><strong>.</strong> Giao Ủy ban nhân dân tỉnh tổ chức thực hiện; giao Thường trực Hội đồng nhân dân tỉnh, các Ban của Hội đồng nhân dân tỉnh, các Tổ đại biểu Hội đồng nhân dân tỉnh và các đại biểu Hội đồng nhân dân tỉnh giám sát việc thực hiện.</p>\n<p style=\"text-align:justify;\">\n\tNghị quyết này đã được Hội đồng nhân dân tỉnh Bình Phước khóa IX, kỳ họp thứ tám thông qua ngày 03 tháng 7 năm 2019 và có hiệu lực từ ngày 15 tháng 7 năm 2019.</p>\n<p style=\"text-align:justify;\">\n\tNghị quyết này thay thế Nghị quyết số 49/2017/NQ-HĐND ngày 12 tháng 12 năm 2017 của Hội đồng nhân dân tỉnh thông qua điều chỉnh quy hoạch sử dụng đất đến năm 2020, kế hoạch sử dụng đất kỳ cuối (2016 - 2020) tỉnh Bình Phước./.</p>\r\n                        </div>\r\n                    </td>\r\n                </tr>\r\n\r\n            </table>"
}