{
  "id": "155782",
  "url": "http://127.0.0.1:5500/detail.html?src=api&id=155782",
  "tieuDe": "Sửa đổi, bổ sung một số điều của Nghị định số 06/2019/NĐ-CP ngày 22 tháng 01 năm 2019 của Chính phủ về quản lý thực vật rừng, động vật rừng nguy cấp, quý, hiếm và thực thi Công ước về buôn bán quốc tế các loài động vật, thực vật hoang dã nguy cấp",
  "soHieu": "84/2021/NĐ-CP",
  "ngayBanHanh": "22/09/2021",
  "ngayHieuLuc": "30/11/2021",
  "loaiVanBan": "Nghị định",
  "coQuanBanHanh": "Chính phủ",
  "tinhTrang": "Hết hiệu lực toàn bộ",
  "nganh": "Nông nghiệp và phát triển nông thôn",
  "linhVuc": "Lâm nghiệp",
  "noiDung": "<table class=\"detailcontent\" width=\"100%\" border=\"0\" id=\"content\">\r\n                <tr>\r\n                    <td colspan=\"3\">\r\n                        <div align=\"justify\">\r\n                            <p align=\"center\">\n\t<strong>NGHỊ ĐỊNH</strong></p>\n<p align=\"center\">\n\t<strong>Sửa đổi, bổ sung một số điều của Nghị định số 06/2019/NĐ-CP ngày 22 tháng 01 năm 2019 của Chính phủ về quản lý thực vật rừng, động vật rừng nguy cấp, quý, hiếm và thực thi Công ước về buôn bán quốc tế các loài động vật, thực vật hoang dã nguy cấp</strong></p>\n<p align=\"center\">\n\t____________________</p>\n<p align=\"center\">\n\t </p>\n<p>\n\t<em>Căn cứ Luật Tổ chức Chính phủ ngày 19 tháng 6 năm 2015; Luật sửa đổi, bổ sung một số điều của Luật Tổ chức Chính phủ và Luật Tổ chức chính quyền địa phương ngày 22 tháng 11 năm 2019;</em></p>\n<p>\n\t<em>Căn cứ Luật Lâm nghiệp ngày 15 tháng 11 năm 2017;</em></p>\n<p>\n\t<em>Căn cứ Luật Thuỷ sản ngày 21 tháng 11 năm 2017;</em></p>\n<p>\n\t<em>Theo đề nghị của Bộ trưởng Bộ Nông nghiệp và Phát triển nông thôn;</em></p>\n<p>\n\t<em>Chính phủ ban hành Nghị định sửa đổi, bổ sung một số điều của Nghị định số 06/2019/NĐ-CP ngày 22 tháng 01 năm 2019 của Chính phủ về quản lý thực vật rừng, động vật rừng nguy cấp, quý, hiếm và thực thi Công ước về buôn bán quốc tế các loài động vật, thực vật hoang dã nguy cấp.</em></p>\n<p>\n\t<strong>Điều 1. Sửa đổi, bổ sung một số điều của Nghị định số 06/2019/NĐ-CP ngày 22 tháng 01 năm 2019 của Chính phủ về quản lý thực vật rừng, động vật rừng nguy cấp, quý, hiếm và thực thi Công ước về buôn bán quốc tế các loài động vật, thực vật hoang dã nguy cấp</strong></p>\n<p>\n\t1. Khoản 6 Điều 3 được sửa đổi, bổ sung như sau:</p>\n<p>\n\t“6. Dẫn xuất của các loài động vật, thực vật là toàn bộ các dạng vật chất được chiết xuất ra từ động vật, thực vật, gồm: máu, xạ, dịch, mật, mỡ của động vật; nhựa, tinh dầu, dịch chiết từ thực vật.”</p>\n<p>\n\t2. Khoản 11 Điều 3 được sửa đổi, bổ sung như sau:</p>\n<p>\n\t“11. Không vì mục đích thương mại là các hoạt động phục vụ ngoại giao, nghiên cứu khoa học, nhân nuôi bảo tồn, nuôi làm cảnh, cứu hộ, trao đổi giữa các vườn động vật, vườn thực vật, bảo tàng; triển lãm trưng bày giới thiệu sản phẩm; biểu diễn xiếc; trao đổi, trao trả mẫu vật giữa các cơ quan quản lý CITES”</p>\n<p>\n\t3. Khoản 18 Điều 3 được sửa đổi, bổ sung như sau:</p>\n<p>\n\t“18. Nuôi sinh trưởng là hình thức nuôi giữ con, trứng, phôi của các loài động vật hoang dã để nuôi lớn, cho ấp nở thành các cá thể trong môi trường có kiểm soát.”</p>\n<p>\n\t4. Bổ sung khoản 29 Điều 3 như sau:</p>\n<p>\n\t“29. Động vật hoang dã, thực vật hoang dã là những loài động vật, thực vật sinh sống, phát triển trong sinh cảnh tự nhiên, nhân tạo hoặc loài động vật, thực vật được nuôi, trồng trong môi trường có kiểm soát nhưng không phải là vật nuôi theo quy định của pháp luật về chăn nuôi, thuộc một trong các trường hợp sau:</p>\n<p>\n\ta) Loài động vật, thực vật nguy cấp, quý, hiếm được ưu tiên bảo vệ;</p>\n<p>\n\tb) Loài thực vật rừng, động vật rừng nguy cấp, quý, hiếm;</p>\n<p>\n\tc) Loài động vật, thực vật hoang dã nguy cấp thuộc các Phụ lục của CITES;</p>\n<p>\n\td) Loài động vật rừng thông thường;</p>\n<p>\n\tđ) Loài động vật trên cạn khác thuộc lớp chim, thú, bò sát, lưỡng cư, trừ một số loài thuộc Danh mục do Bộ Nông nghiệp và Phát triển nông thôn chủ trì, phối hợp với Bộ Tài nguyên và Môi trường và các cơ quan liên quan công bố.”</p>\n<p>\n\t5. Bãi bỏ khoản 3 Điều 9.</p>\n<p>\n\t6. Khoản 1 Điều 14 được sửa đổi, bổ sung như sau:</p>\n<p>\n\t“1. Có phương án nuôi, trồng theo Mẫu số 04, Mẫu số 05, Mẫu số 06 và Mẫu số 07 tại Phụ lục ban hành kèm theo Nghị định này.”</p>\n<p>\n\t7. Khoản 4 Điều 14 được sửa đổi, bổ sung như sau:</p>\n<p>\n\t“4. Trong quá trình nuôi, trồng phải lập sổ theo dõi nuôi, trồng theo Mẫu số 16, Mẫu số 17 tại Phụ lục ban hành kèm theo Nghị định này; định kỳ báo cáo và chịu sự kiểm tra, giám sát của Cơ quan thẩm quyền quản lý CITES Việt Nam, cơ quan quản lý nhà nước về thủy sản, về lâm nghiệp, về môi trường cấp tỉnh.”</p>\n<p>\n\t8. Điểm c khoản 1 Điều 15 được sửa đổi, bổ sung như sau:</p>\n<p>\n\t“c) Các loài động vật hoang dã thuộc Phụ lục CITES thuộc các lớp thú, chim, bò sát lần đầu tiên đăng ký nuôi tại cơ sở phải được Cơ quan khoa học CITES Việt Nam xác nhận bằng văn bản về việc nuôi sinh sản, nuôi sinh trưởng không làm ảnh hưởng đến sự tồn tại của loài nuôi và các loài khác có liên quan trong tự nhiên theo trình tự như sau:</p>\n<p>\n\tTrong thời hạn 02 ngày làm việc kể từ ngày nhận được hồ sơ đăng ký mã số cơ sở, Cơ quan cấp mã số theo quy định tại Nghị định này có trách nhiệm gửi văn bản đề nghị xác nhận đến Cơ quan khoa học CITES Việt Nam.</p>\n<p>\n\tTrong thời hạn 15 ngày làm việc kể từ ngày nhận được văn bản của Cơ quan cấp mã số, Cơ quan khoa học CITES Việt Nam có trách nhiệm trả lời bằng văn bản đối với nội dung xác nhận ảnh hưởng hoặc không ảnh hưởng của việc nuôi sinh sản, nuôi sinh trưởng đến sự tồn tại của loài nuôi và các loài khác có liên quan trong tự nhiên.”</p>\n<p>\n\t9. Khoản 3 Điều 15 được sửa đổi, bổ sung như sau:</p>\n<p>\n\t“3. Trong quá trình nuôi, trồng phải lập sổ theo dõi nuôi, trồng theo Mẫu số 16, Mẫu số 17 tại Phụ lục ban hành kèm theo Nghị định này; định kỳ báo cáo và chịu sự kiểm tra, giám sát của Cơ quan thẩm quyền quản lý CITES Việt Nam, cơ quan quản lý nhà nước về thủy sản, về lâm nghiệp, về môi trường cấp tỉnh.”</p>\n<p>\n\t10. Khoản 2 Điều 16 được sửa đổi, bổ sung như sau:</p>\n<p>\n\t“2. Hình thức thể hiện mã số cơ sở nuôi, cơ sở trồng được quy định tại Mẫu số 08 (Mã số cơ sở nuôi, trồng) tại Phụ lục ban hành kèm theo Nghị định này.”</p>\n<p>\n\t11. Điểm c khoản 2 Điều 19 được sửa đổi, bổ sung như sau:</p>\n<p>\n\t“c) Số lượng không vượt quá theo quy định của Công ước CITES. Cơ quan thẩm quyền quản lý CITES Việt Nam chịu trách nhiệm dịch và công bố kịp thời theo quy định của Công ước CITES.”</p>\n<p>\n\t12. Điểm b khoản 1 Điều 20 được sửa đổi, bổ sung như sau:</p>\n<p>\n\t“b) Mẫu vật động vật xuất khẩu từ thế hệ F2 trở về sau được sinh sản tại cơ sở nuôi đã được cấp mã số theo quy định tại Điều 17 Nghị định này.”</p>\n<p>\n\t13. Điểm c khoản 1 Điều 20 được sửa đổi, bổ sung như sau:</p>\n<p>\n\t“c) Mẫu vật thực vật xuất khẩu từ cơ sở trồng đã được cấp mã số theo quy định tại Điều 17 Nghị định này.”</p>\n<p>\n\t14. Điểm b khoản 2 Điều 20 được sửa đổi, bổ sung như sau:</p>\n<p>\n\t“b) Mẫu vật động vật xuất khẩu từ thế hệ F1 từ cơ sở nuôi được cấp mã số theo quy định tại Điều 18 Nghị định này.”</p>\n<p>\n\t15. Điểm c khoản 2 Điều 20 được sửa đổi, bổ sung như sau:</p>\n<p>\n\t“c) Mẫu vật thực vật xuất khẩu thuộc Phụ lục II, III CITES từ cơ sở trồng đã được cấp mã số theo quy định tại Điều 18 Nghị định này.”</p>\n<p>\n\t16. Khoản 1 Điều 22 được sửa đổi, bổ sung như sau:</p>\n<p>\n\t“1. Giấy phép CITES quy định theo Mẫu số 09 tại Phụ lục ban hành kèm theo Nghị định này áp dụng cho việc xuất khẩu, nhập khẩu, tái xuất khẩu, nhập nội từ biển mẫu vật các loài động vật, thực vật hoang dã nguy cấp thuộc các Phụ lục CITES; xuất khẩu mẫu vật các loài thực vật rừng, động vật rừng nguy cấp, quý, hiếm. Giấy phép CITES phải được ghi đầy đủ thông tin, dán tem CITES hoặc mã hoá, ký và đóng dấu của Cơ quan thẩm quyền quản lý CITES Việt Nam.”</p>\n<p>\n\t17. Điểm c khoản 2 Điều 25 được sửa đổi, bổ sung như sau:</p>\n<p>\n\t“c) Trường hợp nhập khẩu mẫu vật sống của các loài động vật hoang dã để nuôi, giữ: ngoài thành phần hồ sơ quy định tại điểm a, b khoản này, phải đáp ứng quy định tại khoản 2 Điều 14 hoặc điểm b khoản 1 Điều 15 Nghị định này.”</p>\n<p>\n\t18. Điểm b khoản 3 Điều 25 được sửa đổi, bổ sung như sau:</p>\n<p>\n\t“b) Trong thời hạn 08 ngày làm việc, kể từ ngày nhận được hồ sơ hợp lệ, Cơ quan thẩm quyền quản lý CITES Việt Nam có trách nhiệm cấp giấy phép. Trường hợp cần tham vấn Cơ quan khoa học CITES Việt Nam hoặc cơ quan có liên quan của nước xuất khẩu thì Cơ quan thẩm quyền quản lý CITES Việt Nam tổ chức thực hiện, nhưng thời hạn cấp không quá 22 ngày làm việc.</p>\n<p>\n\tTrường hợp hồ sơ không hợp lệ, trong thời hạn 03 ngày làm việc kể từ ngày nhận được hồ sơ, Cơ quan thẩm quyền quản lý CITES Việt Nam thông báo cho tổ chức, cá nhân biết.”</p>\n<p>\n\t19. Khoản 3 Điều 28 được sửa đổi, bổ sung như sau:</p>\n<p>\n\t“3. Tổ chức, cá nhân có trách nhiệm lưu giữ bản chính các chứng từ liên quan theo quy định về thành phần hồ sơ tại Điều 23, Điều 24, Điều 25, Điều 26 và Điều 27 Nghị định này trong 05 năm kể từ ngày nộp hồ sơ và xuất trình với các cơ quan chức năng khi được yêu cầu.”</p>\n<p>\n\t20. Điểm a khoản 3 Điều 32 được sửa đổi, bổ sung như sau:</p>\n<p>\n\t“a) Trường hợp tổ chức, cá nhân trả lại mẫu vật cho nước xuất xứ, hoặc từ chối tiếp nhận lô hàng nhập khẩu thì Cơ quan thẩm quyền quản lý CITES Việt Nam thực hiện việc cấp giấy phép tái xuất khẩu mẫu vật cho nước xuất khẩu theo quy định của Công ước CITES và pháp luật Việt Nam.</p>\n<p>\n\tTrong thời hạn 30 ngày làm việc, kể từ ngày Cơ quan thẩm quyền quản lý CITES Việt Nam thông báo bằng văn bản đến Cơ quan quản lý CITES của nước xuất xứ về mẫu vật vi phạm mà Cơ quan quản lý CITES nước xuất xứ từ chối tiếp nhận, hoặc không phản hồi, hoặc không thực hiện nghĩa vụ theo quy định của Công ước CITES thì mẫu vật được xử lý theo quy định của pháp luật về quản lý tài sản công và theo các nguyên tắc sau:</p>\n<p>\n\tMẫu vật thuộc Phụ lục I CITES chỉ được sử dụng vào mục đích nghiên cứu khoa học, trưng bày giáo dục môi trường, đào tạo, tập huấn, thực thi pháp luật hoặc lưu kho hoặc tiêu hủy theo quy định của pháp luật.</p>\n<p>\n\tMẫu vật thuộc Phụ lục II, III CITES được phép bán đấu giá cho các tổ chức, cá nhân sử dụng không vì mục đích thương mại.”</p>\n<p>\n\t21. Bổ sung khoản 5 Điều 40 như sau:</p>\n<p>\n\t“5. Chế độ quản lý và nuôi các loài động vật hoang dã thuộc điểm đ khoản 29 Điều 3 Nghị định này được thực hiện như đối với loài động vật rừng thông thường.”</p>\n<p>\n\t22. Thay thế Danh mục thực vật rừng, động vật rừng nguy cấp, quý, hiếm ban hành kèm theo Nghị định số 06/2019/NĐ-CP bằng Danh mục thực vật rừng, động vật rừng nguy cấp, quý, hiếm tại Phụ lục I ban hành kèm theo Nghị định này.</p>\n<p>\n\t23. Thay thế Mẫu số 08 (Mã số cơ sở nuôi, trồng), Mẫu số 09 (Mẫu giấy phép CITES), Mẫu số 04 và số 06 (Phương án nuôi) ban hành kèm theo Nghị định số 06/2019/NĐ-CP bằng Mẫu mã số cơ sở nuôi, trồng tại Phụ lục II, Mẫu giấy phép CITES tại Phụ lục III, Mẫu phương án nuôi tại Phụ lục IV ban hành kèm theo Nghị định này.</p>\n<p>\n\t<strong>Điều 2. Hiệu lực thi hành</strong></p>\n<p>\n\tNghị định này có hiệu lực từ ngày 30 tháng 11 năm 2021.</p>\n<p>\n\t<strong>Điều 3. Quy định chuyển tiếp</strong></p>\n<p>\n\t1. Tổ chức, cá nhân đã nộp hồ sơ đề nghị cấp mã số cơ sở nuôi, trồng trước ngày Nghị định này có hiệu lực, nhưng chưa được cơ quan có thẩm quyền giải quyết thì thực hiện theo quy định tại Nghị định số 06/2019/NĐ-CP.</p>\n<p>\n\t2. Đối với các cơ sở nuôi, cơ sở trồng thuộc đối tượng phải đăng ký mã số cơ sở theo quy định tại Nghị định này, trong thời hạn 06 tháng kể từ ngày Nghị định này có hiệu lực thi hành, chủ các cơ sở nuôi, cơ sở trồng phải thực hiện lập hồ sơ đề nghị cấp mã số cơ sở nuôi, cơ sở trồng, gửi cơ quan có thẩm quyền theo quy định của Nghị định số 06/2019/NĐ-CP.</p>\n<p>\n\t<strong>Điều 4. Trách nhiệm thi hành</strong></p>\n<p>\n\t1. Bộ Nông nghiệp và Phát triển nông thôn chủ trì, phối hợp với Bộ Tài nguyên và Môi trường và các cơ quan liên quan công bố Danh mục loài động vật hoang dã theo quy định tại điểm đ khoản 29 Điều 3 Nghị định số 06/2019/NĐ-CP trước ngày 30 tháng 11 năm 2021, định kỳ rà soát, điều chỉnh 3 năm một lần hoặc khi cần thiết.</p>\n<p>\n\t2. Các Bộ trưởng, Thủ trưởng cơ quan ngang bộ, Thủ trưởng cơ quan thuộc Chính phủ, Chủ tịch Ủy ban nhân dân các tỉnh, thành phố trực thuộc trung ương và các cơ quan, tổ chức, cá nhân có liên quan chịu trách nhiệm thi hành Nghị định này./.</p>\r\n                        </div>\r\n                    </td>\r\n                </tr>\r\n\r\n            </table>"
}