{
  "id": "167074",
  "url": "http://127.0.0.1:5500/detail.html?src=api&id=167074",
  "tieuDe": "Nghị quyết sửa đổi, bổ sung một số nội dung tại Phụ lục ban hành kèm theo Nghị quyết số 44/2021/NQ-HĐND ngày 16 tháng 12 năm 2021 của Hội đồng nhân dân tỉnh về một số cơ chế, chính sách hỗ trợ tạo nguồn lực xây dựng thành công tỉnh Hà Tĩnh đạt chuẩn nông thôn mới, giai đoạn 2022 – 2025",
  "soHieu": "124/2024/NQ-HĐND",
  "ngayBanHanh": "04/05/2024",
  "ngayHieuLuc": "15/05/2024",
  "loaiVanBan": "Nghị quyết",
  "coQuanBanHanh": "HĐND tỉnh Hà Tĩnh",
  "tinhTrang": "Hết hiệu lực toàn bộ",
  "nganh": "Nông nghiệp và phát triển nông thôn Tài chính",
  "linhVuc": "Nông thôn mới Tài chính",
  "noiDung": "<table class=\"detailcontent\" width=\"100%\" border=\"0\" id=\"content\">\r\n                <tr>\r\n                    <td colspan=\"3\">\r\n                        <div align=\"justify\">\r\n                            \r\n                        </div>\r\n                    </td>\r\n                </tr>\r\n\r\n            </table>"
}